README.md
pyproject.toml
src/faststruct/__init__.py
src/faststruct/_faststruct.c
src/faststruct_simple.egg-info/PKG-INFO
src/faststruct_simple.egg-info/SOURCES.txt
src/faststruct_simple.egg-info/dependency_links.txt
src/faststruct_simple.egg-info/top_level.txt