Metadata-Version: 2.4
Name: faststruct-simple
Version: 0.0.1
Summary: Simple and experimental fast binary dict serializer (CPython C extension)
Author: Karen Ward
License: MIT
Requires-Python: >=3.9
